{	"result": {		"players": [			{				"account_id": 283142068,				"player_slot": 0,				"hero_id": 84,				"item_0": 180,				"item_1": 121,				"item_2": 100,				"item_3": 108,				"item_4": 0,				"item_5": 0,				"kills": 10,				"deaths": 3,				"assists": 16,				"leaver_status": 0,				"gold": 253,				"last_hits": 46,				"denies": 4,				"gold_per_min": 388,				"xp_per_min": 508,				"gold_spent": 15230,				"hero_damage": 10008,				"tower_damage": 562,				"hero_healing": 0,				"level": 19,				"ability_upgrades": [					{						"ability": 5438,						"time": 338,						"level": 1					},					{						"ability": 5439,						"time": 508,						"level": 2					},					{						"ability": 5440,						"time": 605,						"level": 3					},					{						"ability": 5438,						"time": 725,						"level": 4					},					{						"ability": 5438,						"time": 847,						"level": 5					},					{						"ability": 5441,						"time": 933,						"level": 6					},					{						"ability": 5438,						"time": 1145,						"level": 7					},					{						"ability": 5439,						"time": 1333,						"level": 8					},					{						"ability": 5439,						"time": 1507,						"level": 9					},					{						"ability": 5439,						"time": 1611,						"level": 10					},					{						"ability": 5440,						"time": 1700,						"level": 11					},					{						"ability": 5441,						"time": 1991,						"level": 12					},					{						"ability": 5440,						"time": 2078,						"level": 13					},					{						"ability": 5440,						"time": 2230,						"level": 14					},					{						"ability": 5002,						"time": 2290,						"level": 15					},					{						"ability": 5441,						"time": 2398,						"level": 16					},					{						"ability": 5002,						"time": 2511,						"level": 17					},					{						"ability": 5002,						"time": 2704,						"level": 18					},					{						"ability": 5002,						"time": 2771,						"level": 19					}				]							},			{				"account_id": 4294967295,				"player_slot": 1,				"hero_id": 75,				"item_0": 102,				"item_1": 50,				"item_2": 108,				"item_3": 40,				"item_4": 41,				"item_5": 42,				"kills": 2,				"deaths": 3,				"assists": 20,				"leaver_status": 0,				"gold": 325,				"last_hits": 37,				"denies": 3,				"gold_per_min": 310,				"xp_per_min": 433,				"gold_spent": 12475,				"hero_damage": 12410,				"tower_damage": 443,				"hero_healing": 0,				"level": 18,				"ability_upgrades": [					{						"ability": 5377,						"time": 393,						"level": 1					},					{						"ability": 5379,						"time": 491,						"level": 2					},					{						"ability": 5377,						"time": 532,						"level": 3					},					{						"ability": 5379,						"time": 604,						"level": 4					},					{						"ability": 5379,						"time": 720,						"level": 5					},					{						"ability": 5380,						"time": 822,						"level": 6					},					{						"ability": 5378,						"time": 960,						"level": 7					},					{						"ability": 5379,						"time": 1017,						"level": 8					},					{						"ability": 5377,						"time": 1246,						"level": 9					},					{						"ability": 5378,						"time": 1472,						"level": 10					},					{						"ability": 5380,						"time": 1634,						"level": 11					},					{						"ability": 5377,						"time": 2139,						"level": 12					},					{						"ability": 5378,						"time": 2153,						"level": 13					},					{						"ability": 5378,						"time": 2374,						"level": 14					},					{						"ability": 5002,						"time": 2422,						"level": 15					},					{						"ability": 5002,						"time": 2654,						"level": 16					},					{						"ability": 5380,						"time": 2733,						"level": 17					}				]							},			{				"account_id": 4294967295,				"player_slot": 2,				"hero_id": 8,				"item_0": 50,				"item_1": 116,				"item_2": 81,				"item_3": 145,				"item_4": 108,				"item_5": 0,				"kills": 14,				"deaths": 4,				"assists": 16,				"leaver_status": 0,				"gold": 2843,				"last_hits": 161,				"denies": 3,				"gold_per_min": 498,				"xp_per_min": 584,				"gold_spent": 16940,				"hero_damage": 15121,				"tower_damage": 2420,				"hero_healing": 899,				"level": 21,				"ability_upgrades": [					{						"ability": 5027,						"time": 343,						"level": 1					},					{						"ability": 5028,						"time": 486,						"level": 2					},					{						"ability": 5027,						"time": 572,						"level": 3					},					{						"ability": 5029,						"time": 705,						"level": 4					},					{						"ability": 5027,						"time": 807,						"level": 5					},					{						"ability": 5030,						"time": 1101,						"level": 6					},					{						"ability": 5028,						"time": 1201,						"level": 7					},					{						"ability": 5027,						"time": 1351,						"level": 8					},					{						"ability": 5028,						"time": 1470,						"level": 9					},					{						"ability": 5028,						"time": 1556,						"level": 10					},					{						"ability": 5029,						"time": 1592,						"level": 11					},					{						"ability": 5030,						"time": 1797,						"level": 12					},					{						"ability": 5029,						"time": 1840,						"level": 13					},					{						"ability": 5029,						"time": 2020,						"level": 14					},					{						"ability": 5002,						"time": 2135,						"level": 15					},					{						"ability": 5030,						"time": 2181,						"level": 16					},					{						"ability": 5002,						"time": 2319,						"level": 17					},					{						"ability": 5002,						"time": 2427,						"level": 18					},					{						"ability": 5002,						"time": 2578,						"level": 19					}				]							},			{				"account_id": 4294967295,				"player_slot": 3,				"hero_id": 44,				"item_0": 116,				"item_1": 164,				"item_2": 46,				"item_3": 135,				"item_4": 145,				"item_5": 63,				"kills": 11,				"deaths": 4,				"assists": 10,				"leaver_status": 0,				"gold": 2939,				"last_hits": 248,				"denies": 1,				"gold_per_min": 567,				"xp_per_min": 704,				"gold_spent": 19325,				"hero_damage": 13117,				"tower_damage": 1783,				"hero_healing": 0,				"level": 23,				"ability_upgrades": [					{						"ability": 5190,						"time": 343,						"level": 1					},					{						"ability": 5191,						"time": 519,						"level": 2					},					{						"ability": 5190,						"time": 603,						"level": 3					},					{						"ability": 5192,						"time": 729,						"level": 4					},					{						"ability": 5190,						"time": 854,						"level": 5					},					{						"ability": 5193,						"time": 1027,						"level": 6					},					{						"ability": 5192,						"time": 1144,						"level": 7					},					{						"ability": 5191,						"time": 1225,						"level": 8					},					{						"ability": 5190,						"time": 1383,						"level": 9					},					{						"ability": 5191,						"time": 1470,						"level": 10					},					{						"ability": 5193,						"time": 1526,						"level": 11					},					{						"ability": 5191,						"time": 1759,						"level": 12					},					{						"ability": 5192,						"time": 1829,						"level": 13					},					{						"ability": 5192,						"time": 1955,						"level": 14					},					{						"ability": 5002,						"time": 2017,						"level": 15					},					{						"ability": 5193,						"time": 2037,						"level": 16					},					{						"ability": 5002,						"time": 2100,						"level": 17					},					{						"ability": 5002,						"time": 2318,						"level": 18					},					{						"ability": 5002,						"time": 2436,						"level": 19					},					{						"ability": 5002,						"time": 2538,						"level": 20					},					{						"ability": 5002,						"time": 2645,						"level": 21					},					{						"ability": 5002,						"time": 2731,						"level": 22					}				]							},			{				"account_id": 116861198,				"player_slot": 4,				"hero_id": 23,				"item_0": 48,				"item_1": 249,				"item_2": 149,				"item_3": 46,				"item_4": 0,				"item_5": 0,				"kills": 7,				"deaths": 7,				"assists": 16,				"leaver_status": 0,				"gold": 449,				"last_hits": 116,				"denies": 3,				"gold_per_min": 413,				"xp_per_min": 431,				"gold_spent": 17760,				"hero_damage": 8752,				"tower_damage": 1990,				"hero_healing": 0,				"level": 18,				"ability_upgrades": [					{						"ability": 5031,						"time": 372,						"level": 1					},					{						"ability": 5032,						"time": 527,						"level": 2					},					{						"ability": 5031,						"time": 634,						"level": 3					},					{						"ability": 5032,						"time": 688,						"level": 4					},					{						"ability": 5031,						"time": 785,						"level": 5					},					{						"ability": 5035,						"time": 1046,						"level": 6					},					{						"ability": 5032,						"time": 1099,						"level": 7					},					{						"ability": 5031,						"time": 1255,						"level": 8					},					{						"ability": 5032,						"time": 1477,						"level": 9					},					{						"ability": 5033,						"time": 1615,						"level": 10					},					{						"ability": 5035,						"time": 1734,						"level": 11					},					{						"ability": 5033,						"time": 2058,						"level": 12					},					{						"ability": 5033,						"time": 2127,						"level": 13					},					{						"ability": 5033,						"time": 2293,						"level": 14					},					{						"ability": 5002,						"time": 2365,						"level": 15					},					{						"ability": 5035,						"time": 2425,						"level": 16					},					{						"ability": 5002,						"time": 2538,						"level": 17					}				]							},			{				"account_id": 182943947,				"player_slot": 128,				"hero_id": 9,				"item_0": 63,				"item_1": 36,				"item_2": 51,				"item_3": 75,				"item_4": 75,				"item_5": 75,				"kills": 1,				"deaths": 11,				"assists": 6,				"leaver_status": 0,				"gold": 561,				"last_hits": 58,				"denies": 2,				"gold_per_min": 244,				"xp_per_min": 242,				"gold_spent": 7655,				"hero_damage": 5642,				"tower_damage": 217,				"hero_healing": 0,				"level": 13,				"ability_upgrades": [					{						"ability": 5048,						"time": 380,						"level": 1					},					{						"ability": 5050,						"time": 506,						"level": 2					},					{						"ability": 5048,						"time": 599,						"level": 3					},					{						"ability": 5051,						"time": 755,						"level": 4					},					{						"ability": 5048,						"time": 862,						"level": 5					},					{						"ability": 5051,						"time": 1192,						"level": 6					},					{						"ability": 5048,						"time": 1354,						"level": 7					},					{						"ability": 5051,						"time": 1556,						"level": 8					},					{						"ability": 5050,						"time": 1822,						"level": 9					},					{						"ability": 5051,						"time": 2017,						"level": 10					},					{						"ability": 5049,						"time": 2256,						"level": 11					},					{						"ability": 5049,						"time": 2430,						"level": 12					},					{						"ability": 5050,						"time": 2595,						"level": 13					}				]							},			{				"account_id": 4294967295,				"player_slot": 129,				"hero_id": 69,				"item_0": 48,				"item_1": 119,				"item_2": 0,				"item_3": 1,				"item_4": 81,				"item_5": 182,				"kills": 7,				"deaths": 7,				"assists": 4,				"leaver_status": 0,				"gold": 384,				"last_hits": 95,				"denies": 2,				"gold_per_min": 347,				"xp_per_min": 354,				"gold_spent": 12400,				"hero_damage": 6281,				"tower_damage": 156,				"hero_healing": 441,				"level": 16,				"ability_upgrades": [					{						"ability": 5339,						"time": 344,						"level": 1					},					{						"ability": 5340,						"time": 513,						"level": 2					},					{						"ability": 5341,						"time": 595,						"level": 3					},					{						"ability": 5341,						"time": 667,						"level": 4					},					{						"ability": 5340,						"time": 822,						"level": 5					},					{						"ability": 5342,						"time": 946,						"level": 6					},					{						"ability": 5341,						"time": 1035,						"level": 7					},					{						"ability": 5340,						"time": 1161,						"level": 8					},					{						"ability": 5341,						"time": 1402,						"level": 9					},					{						"ability": 5340,						"time": 1516,						"level": 10					},					{						"ability": 5342,						"time": 1708,						"level": 11					},					{						"ability": 5339,						"time": 2237,						"level": 12					},					{						"ability": 5339,						"time": 2432,						"level": 13					},					{						"ability": 5339,						"time": 2432,						"level": 14					},					{						"ability": 5002,						"time": 2481,						"level": 15					},					{						"ability": 5342,						"time": 2714,						"level": 16					}				]							},			{				"account_id": 4294967295,				"player_slot": 130,				"hero_id": 51,				"item_0": 50,				"item_1": 36,				"item_2": 182,				"item_3": 127,				"item_4": 108,				"item_5": 0,				"kills": 6,				"deaths": 9,				"assists": 8,				"leaver_status": 0,				"gold": 484,				"last_hits": 87,				"denies": 4,				"gold_per_min": 284,				"xp_per_min": 261,				"gold_spent": 8830,				"hero_damage": 14510,				"tower_damage": 316,				"hero_healing": 0,				"level": 13,				"ability_upgrades": [					{						"ability": 5239,						"time": 404,						"level": 1					},					{						"ability": 5237,						"time": 506,						"level": 2					},					{						"ability": 5239,						"time": 598,						"level": 3					},					{						"ability": 5238,						"time": 652,						"level": 4					},					{						"ability": 5239,						"time": 691,						"level": 5					},					{						"ability": 5240,						"time": 834,						"level": 6					},					{						"ability": 5237,						"time": 1020,						"level": 7					},					{						"ability": 5239,						"time": 1113,						"level": 8					},					{						"ability": 5237,						"time": 1293,						"level": 9					},					{						"ability": 5237,						"time": 1693,						"level": 10					},					{						"ability": 5240,						"time": 1928,						"level": 11					},					{						"ability": 5238,						"time": 2420,						"level": 12					},					{						"ability": 5238,						"time": 2592,						"level": 13					}				]							},			{				"account_id": 4294967295,				"player_slot": 131,				"hero_id": 11,				"item_0": 63,				"item_1": 75,				"item_2": 41,				"item_3": 135,				"item_4": 0,				"item_5": 152,				"kills": 5,				"deaths": 7,				"assists": 5,				"leaver_status": 0,				"gold": 786,				"last_hits": 169,				"denies": 11,				"gold_per_min": 349,				"xp_per_min": 396,				"gold_spent": 11435,				"hero_damage": 9647,				"tower_damage": 940,				"hero_healing": 0,				"level": 17,				"ability_upgrades": [					{						"ability": 5062,						"time": 448,						"level": 1					},					{						"ability": 5059,						"time": 474,						"level": 2					},					{						"ability": 5059,						"time": 514,						"level": 3					},					{						"ability": 5062,						"time": 570,						"level": 4					},					{						"ability": 5059,						"time": 643,						"level": 5					},					{						"ability": 5062,						"time": 755,						"level": 6					},					{						"ability": 5059,						"time": 853,						"level": 7					},					{						"ability": 5062,						"time": 932,						"level": 8					},					{						"ability": 5064,						"time": 1109,						"level": 9					},					{						"ability": 5063,						"time": 1225,						"level": 10					},					{						"ability": 5002,						"time": 1305,						"level": 11					},					{						"ability": 5063,						"time": 1667,						"level": 12					},					{						"ability": 5064,						"time": 1839,						"level": 13					},					{						"ability": 5063,						"time": 2065,						"level": 14					},					{						"ability": 5063,						"time": 2239,						"level": 15					},					{						"ability": 5064,						"time": 2549,						"level": 16					},					{						"ability": 5002,						"time": 2680,						"level": 17					}				]							},			{				"account_id": 4294967295,				"player_slot": 132,				"hero_id": 25,				"item_0": 100,				"item_1": 36,				"item_2": 180,				"item_3": 46,				"item_4": 1,				"item_5": 0,				"kills": 2,				"deaths": 11,				"assists": 8,				"leaver_status": 0,				"gold": 522,				"last_hits": 84,				"denies": 1,				"gold_per_min": 280,				"xp_per_min": 356,				"gold_spent": 8070,				"hero_damage": 9250,				"tower_damage": 76,				"hero_healing": 0,				"level": 16,				"ability_upgrades": [					{						"ability": 5040,						"time": 341,						"level": 1					},					{						"ability": 5041,						"time": 514,						"level": 2					},					{						"ability": 5040,						"time": 613,						"level": 3					},					{						"ability": 5042,						"time": 741,						"level": 4					},					{						"ability": 5040,						"time": 913,						"level": 5					},					{						"ability": 5043,						"time": 1087,						"level": 6					},					{						"ability": 5040,						"time": 1195,						"level": 7					},					{						"ability": 5041,						"time": 1290,						"level": 8					},					{						"ability": 5041,						"time": 1513,						"level": 9					},					{						"ability": 5042,						"time": 1825,						"level": 10					},					{						"ability": 5043,						"time": 1924,						"level": 11					},					{						"ability": 5041,						"time": 2145,						"level": 12					},					{						"ability": 5042,						"time": 2146,						"level": 13					},					{						"ability": 5002,						"time": 2417,						"level": 14					},					{						"ability": 5002,						"time": 2417,						"level": 15					},					{						"ability": 5043,						"time": 2682,						"level": 16					}				]							}		]		,		"radiant_win": true,		"duration": 2365,		"start_time": 1447518906,		"match_id": 1935495131,		"match_seq_num": 1710003576,		"tower_status_radiant": 1980,		"tower_status_dire": 260,		"barracks_status_radiant": 63,		"barracks_status_dire": 51,		"cluster": 153,		"first_blood_time": 166,		"lobby_type": 7,		"human_players": 10,		"leagueid": 0,		"positive_votes": 0,		"negative_votes": 0,		"game_mode": 22,		"engine": 1	}}