{	"result": {		"players": [			{				"account_id": 4294967295,				"player_slot": 0,				"hero_id": 46,				"item_0": 63,				"item_1": 1,				"item_2": 36,				"item_3": 168,				"item_4": 149,				"item_5": 0,				"kills": 10,				"deaths": 8,				"assists": 11,				"leaver_status": 0,				"gold": 1747,				"last_hits": 121,				"denies": 0,				"gold_per_min": 338,				"xp_per_min": 362,				"gold_spent": 10570,				"hero_damage": 12032,				"tower_damage": 703,				"hero_healing": 0,				"level": 17,				"ability_upgrades": [					{						"ability": 5196,						"time": 178,						"level": 1					},					{						"ability": 5194,						"time": 262,						"level": 2					},					{						"ability": 5194,						"time": 308,						"level": 3					},					{						"ability": 5195,						"time": 361,						"level": 4					},					{						"ability": 5194,						"time": 458,						"level": 5					},					{						"ability": 5197,						"time": 512,						"level": 6					},					{						"ability": 5196,						"time": 624,						"level": 7					},					{						"ability": 5196,						"time": 707,						"level": 8					},					{						"ability": 5195,						"time": 1040,						"level": 9					},					{						"ability": 5194,						"time": 1246,						"level": 10					},					{						"ability": 5197,						"time": 1434,						"level": 11					},					{						"ability": 5196,						"time": 1743,						"level": 12					},					{						"ability": 5195,						"time": 1756,						"level": 13					},					{						"ability": 5195,						"time": 1945,						"level": 14					},					{						"ability": 5002,						"time": 2073,						"level": 15					},					{						"ability": 5197,						"time": 2501,						"level": 16					},					{						"ability": 5002,						"time": 2577,						"level": 17					}				]							},			{				"account_id": 4294967295,				"player_slot": 1,				"hero_id": 61,				"item_0": 98,				"item_1": 63,				"item_2": 81,				"item_3": 32,				"item_4": 0,				"item_5": 10,				"kills": 7,				"deaths": 10,				"assists": 10,				"leaver_status": 0,				"gold": 151,				"last_hits": 107,				"denies": 8,				"gold_per_min": 310,				"xp_per_min": 341,				"gold_spent": 11850,				"hero_damage": 10471,				"tower_damage": 1133,				"hero_healing": 301,				"level": 16,				"ability_upgrades": [					{						"ability": 5280,						"time": 150,						"level": 1					},					{						"ability": 5281,						"time": 321,						"level": 2					},					{						"ability": 5279,						"time": 377,						"level": 3					},					{						"ability": 5279,						"time": 466,						"level": 4					},					{						"ability": 5280,						"time": 577,						"level": 5					},					{						"ability": 5280,						"time": 686,						"level": 6					},					{						"ability": 5282,						"time": 726,						"level": 7					},					{						"ability": 5280,						"time": 880,						"level": 8					},					{						"ability": 5281,						"time": 1223,						"level": 9					},					{						"ability": 5279,						"time": 1342,						"level": 10					},					{						"ability": 5282,						"time": 1389,						"level": 11					},					{						"ability": 5279,						"time": 1674,						"level": 12					},					{						"ability": 5281,						"time": 1794,						"level": 13					},					{						"ability": 5281,						"time": 2093,						"level": 14					},					{						"ability": 5002,						"time": 2407,						"level": 15					},					{						"ability": 5282,						"time": 2576,						"level": 16					}				]							},			{				"account_id": 117693603,				"player_slot": 2,				"hero_id": 35,				"item_0": 212,				"item_1": 63,				"item_2": 147,				"item_3": 149,				"item_4": 46,				"item_5": 172,				"kills": 7,				"deaths": 7,				"assists": 10,				"leaver_status": 0,				"gold": 294,				"last_hits": 172,				"denies": 4,				"gold_per_min": 367,				"xp_per_min": 457,				"gold_spent": 14380,				"hero_damage": 19784,				"tower_damage": 772,				"hero_healing": 0,				"level": 19,				"ability_upgrades": [					{						"ability": 5154,						"time": 168,						"level": 1					},					{						"ability": 5156,						"time": 295,						"level": 2					},					{						"ability": 5155,						"time": 360,						"level": 3					},					{						"ability": 5156,						"time": 437,						"level": 4					},					{						"ability": 5154,						"time": 570,						"level": 5					},					{						"ability": 5157,						"time": 691,						"level": 6					},					{						"ability": 5156,						"time": 824,						"level": 7					},					{						"ability": 5156,						"time": 934,						"level": 8					},					{						"ability": 5154,						"time": 1195,						"level": 9					},					{						"ability": 5154,						"time": 1417,						"level": 10					},					{						"ability": 5157,						"time": 1463,						"level": 11					},					{						"ability": 5155,						"time": 1731,						"level": 12					},					{						"ability": 5002,						"time": 1734,						"level": 13					},					{						"ability": 5155,						"time": 1927,						"level": 14					},					{						"ability": 5155,						"time": 1927,						"level": 15					},					{						"ability": 5157,						"time": 2095,						"level": 16					},					{						"ability": 5002,						"time": 2341,						"level": 17					},					{						"ability": 5002,						"time": 2405,						"level": 18					},					{						"ability": 5002,						"time": 2634,						"level": 19					}				]							},			{				"account_id": 4294967295,				"player_slot": 3,				"hero_id": 110,				"item_0": 214,				"item_1": 79,				"item_2": 46,				"item_3": 162,				"item_4": 9,				"item_5": 0,				"kills": 2,				"deaths": 10,				"assists": 18,				"leaver_status": 0,				"gold": 1252,				"last_hits": 56,				"denies": 6,				"gold_per_min": 237,				"xp_per_min": 280,				"gold_spent": 7670,				"hero_damage": 10339,				"tower_damage": 279,				"hero_healing": 796,				"level": 15,				"ability_upgrades": [					{						"ability": 5623,						"time": 228,						"level": 1					},					{						"ability": 5625,						"time": 350,						"level": 2					},					{						"ability": 5625,						"time": 438,						"level": 3					},					{						"ability": 5623,						"time": 536,						"level": 4					},					{						"ability": 5625,						"time": 758,						"level": 5					},					{						"ability": 5630,						"time": 841,						"level": 6					},					{						"ability": 5625,						"time": 1004,						"level": 7					},					{						"ability": 5623,						"time": 1111,						"level": 8					},					{						"ability": 5623,						"time": 1421,						"level": 9					},					{						"ability": 5626,						"time": 1615,						"level": 10					},					{						"ability": 5630,						"time": 1747,						"level": 11					},					{						"ability": 5626,						"time": 2040,						"level": 12					},					{						"ability": 5626,						"time": 2252,						"level": 13					},					{						"ability": 5626,						"time": 2495,						"level": 14					},					{						"ability": 5002,						"time": 2610,						"level": 15					}				]							},			{				"account_id": 4294967295,				"player_slot": 4,				"hero_id": 62,				"item_0": 50,				"item_1": 116,				"item_2": 0,				"item_3": 0,				"item_4": 168,				"item_5": 0,				"kills": 5,				"deaths": 8,				"assists": 11,				"leaver_status": 0,				"gold": 256,				"last_hits": 37,				"denies": 0,				"gold_per_min": 288,				"xp_per_min": 242,				"gold_spent": 10420,				"hero_damage": 8717,				"tower_damage": 0,				"hero_healing": 0,				"level": 14,				"ability_upgrades": [					{						"ability": 5287,						"time": 159,						"level": 1					},					{						"ability": 5286,						"time": 289,						"level": 2					},					{						"ability": 5285,						"time": 407,						"level": 3					},					{						"ability": 5285,						"time": 512,						"level": 4					},					{						"ability": 5287,						"time": 778,						"level": 5					},					{						"ability": 5288,						"time": 903,						"level": 6					},					{						"ability": 5285,						"time": 965,						"level": 7					},					{						"ability": 5286,						"time": 1181,						"level": 8					},					{						"ability": 5287,						"time": 1495,						"level": 9					},					{						"ability": 5285,						"time": 1830,						"level": 10					},					{						"ability": 5288,						"time": 1870,						"level": 11					},					{						"ability": 5286,						"time": 2579,						"level": 12					},					{						"ability": 5287,						"time": 2580,						"level": 13					}				]							},			{				"account_id": 4294967295,				"player_slot": 128,				"hero_id": 20,				"item_0": 212,				"item_1": 63,				"item_2": 102,				"item_3": 0,				"item_4": 170,				"item_5": 0,				"kills": 4,				"deaths": 9,				"assists": 16,				"leaver_status": 0,				"gold": 3381,				"last_hits": 95,				"denies": 6,				"gold_per_min": 361,				"xp_per_min": 410,				"gold_spent": 11555,				"hero_damage": 9527,				"tower_damage": 1632,				"hero_healing": 0,				"level": 18,				"ability_upgrades": [					{						"ability": 5122,						"time": 172,						"level": 1					},					{						"ability": 5124,						"time": 311,						"level": 2					},					{						"ability": 5123,						"time": 412,						"level": 3					},					{						"ability": 5122,						"time": 498,						"level": 4					},					{						"ability": 5122,						"time": 677,						"level": 5					},					{						"ability": 5125,						"time": 789,						"level": 6					},					{						"ability": 5123,						"time": 878,						"level": 7					},					{						"ability": 5123,						"time": 1043,						"level": 8					},					{						"ability": 5122,						"time": 1067,						"level": 9					},					{						"ability": 5123,						"time": 1281,						"level": 10					},					{						"ability": 5125,						"time": 1359,						"level": 11					},					{						"ability": 5124,						"time": 1639,						"level": 12					},					{						"ability": 5124,						"time": 1730,						"level": 13					},					{						"ability": 5124,						"time": 1994,						"level": 14					},					{						"ability": 5002,						"time": 2206,						"level": 15					},					{						"ability": 5125,						"time": 2331,						"level": 16					},					{						"ability": 5002,						"time": 2459,						"level": 17					},					{						"ability": 5002,						"time": 2808,						"level": 18					}				]							},			{				"account_id": 4294967295,				"player_slot": 129,				"hero_id": 41,				"item_0": 71,				"item_1": 63,				"item_2": 172,				"item_3": 141,				"item_4": 0,				"item_5": 51,				"kills": 6,				"deaths": 7,				"assists": 16,				"leaver_status": 0,				"gold": 3872,				"last_hits": 120,				"denies": 10,				"gold_per_min": 406,				"xp_per_min": 413,				"gold_spent": 12830,				"hero_damage": 11118,				"tower_damage": 2641,				"hero_healing": 0,				"level": 18,				"ability_upgrades": [					{						"ability": 5182,						"time": 256,						"level": 1					},					{						"ability": 5184,						"time": 321,						"level": 2					},					{						"ability": 5183,						"time": 355,						"level": 3					},					{						"ability": 5184,						"time": 402,						"level": 4					},					{						"ability": 5184,						"time": 611,						"level": 5					},					{						"ability": 5185,						"time": 669,						"level": 6					},					{						"ability": 5184,						"time": 815,						"level": 7					},					{						"ability": 5183,						"time": 1145,						"level": 8					},					{						"ability": 5183,						"time": 1276,						"level": 9					},					{						"ability": 5183,						"time": 1419,						"level": 10					},					{						"ability": 5185,						"time": 1452,						"level": 11					},					{						"ability": 5182,						"time": 1829,						"level": 12					},					{						"ability": 5182,						"time": 1910,						"level": 13					},					{						"ability": 5182,						"time": 2182,						"level": 14					},					{						"ability": 5002,						"time": 2341,						"level": 15					},					{						"ability": 5185,						"time": 2584,						"level": 16					},					{						"ability": 5002,						"time": 2585,						"level": 17					},					{						"ability": 5002,						"time": 2798,						"level": 18					}				]							},			{				"account_id": 187482793,				"player_slot": 130,				"hero_id": 36,				"item_0": 96,				"item_1": 108,				"item_2": 218,				"item_3": 231,				"item_4": 15,				"item_5": 0,				"kills": 13,				"deaths": 4,				"assists": 20,				"leaver_status": 0,				"gold": 1536,				"last_hits": 116,				"denies": 1,				"gold_per_min": 432,				"xp_per_min": 519,				"gold_spent": 18985,				"hero_damage": 13841,				"tower_damage": 1636,				"hero_healing": 5272,				"level": 20,				"ability_upgrades": [					{						"ability": 5158,						"time": 170,						"level": 1					},					{						"ability": 5160,						"time": 335,						"level": 2					},					{						"ability": 5160,						"time": 387,						"level": 3					},					{						"ability": 5159,						"time": 521,						"level": 4					},					{						"ability": 5160,						"time": 679,						"level": 5					},					{						"ability": 5161,						"time": 752,						"level": 6					},					{						"ability": 5158,						"time": 913,						"level": 7					},					{						"ability": 5158,						"time": 917,						"level": 8					},					{						"ability": 5158,						"time": 1108,						"level": 9					},					{						"ability": 5160,						"time": 1211,						"level": 10					},					{						"ability": 5161,						"time": 1237,						"level": 11					},					{						"ability": 5159,						"time": 1669,						"level": 12					},					{						"ability": 5159,						"time": 1791,						"level": 13					},					{						"ability": 5159,						"time": 1917,						"level": 14					},					{						"ability": 5002,						"time": 2213,						"level": 15					},					{						"ability": 5002,						"time": 2378,						"level": 16					},					{						"ability": 5161,						"time": 2404,						"level": 17					},					{						"ability": 5002,						"time": 2458,						"level": 18					},					{						"ability": 5002,						"time": 2582,						"level": 19					},					{						"ability": 5002,						"time": 2694,						"level": 20					}				]							},			{				"account_id": 222117678,				"player_slot": 131,				"hero_id": 17,				"item_0": 98,				"item_1": 41,				"item_2": 46,				"item_3": 121,				"item_4": 48,				"item_5": 77,				"kills": 15,				"deaths": 4,				"assists": 14,				"leaver_status": 0,				"gold": 3878,				"last_hits": 99,				"denies": 12,				"gold_per_min": 444,				"xp_per_min": 446,				"gold_spent": 15870,				"hero_damage": 18147,				"tower_damage": 2273,				"hero_healing": 710,				"level": 19,				"ability_upgrades": [					{						"ability": 5098,						"time": 264,						"level": 1					},					{						"ability": 5100,						"time": 293,						"level": 2					},					{						"ability": 5098,						"time": 326,						"level": 3					},					{						"ability": 5100,						"time": 397,						"level": 4					},					{						"ability": 5099,						"time": 436,						"level": 5					},					{						"ability": 5101,						"time": 507,						"level": 6					},					{						"ability": 5100,						"time": 649,						"level": 7					},					{						"ability": 5100,						"time": 714,						"level": 8					},					{						"ability": 5098,						"time": 1034,						"level": 9					},					{						"ability": 5099,						"time": 1075,						"level": 10					},					{						"ability": 5098,						"time": 1180,						"level": 11					},					{						"ability": 5101,						"time": 1524,						"level": 12					},					{						"ability": 5099,						"time": 1577,						"level": 13					},					{						"ability": 5099,						"time": 1798,						"level": 14					},					{						"ability": 5002,						"time": 1929,						"level": 15					},					{						"ability": 5101,						"time": 2201,						"level": 16					},					{						"ability": 5002,						"time": 2404,						"level": 17					},					{						"ability": 5002,						"time": 2628,						"level": 18					},					{						"ability": 5002,						"time": 2806,						"level": 19					}				]							},			{				"account_id": 218119013,				"player_slot": 132,				"hero_id": 78,				"item_0": 46,				"item_1": 1,				"item_2": 50,				"item_3": 185,				"item_4": 210,				"item_5": 41,				"kills": 3,				"deaths": 7,				"assists": 14,				"leaver_status": 0,				"gold": 2014,				"last_hits": 80,				"denies": 3,				"gold_per_min": 327,				"xp_per_min": 345,				"gold_spent": 12205,				"hero_damage": 7580,				"tower_damage": 1210,				"hero_healing": 0,				"level": 16,				"ability_upgrades": [					{						"ability": 5400,						"time": 407,						"level": 1					},					{						"ability": 5402,						"time": 513,						"level": 2					},					{						"ability": 5400,						"time": 587,						"level": 3					},					{						"ability": 5402,						"time": 677,						"level": 4					},					{						"ability": 5400,						"time": 846,						"level": 5					},					{						"ability": 5403,						"time": 1033,						"level": 6					},					{						"ability": 5400,						"time": 1159,						"level": 7					},					{						"ability": 5402,						"time": 1544,						"level": 8					},					{						"ability": 5402,						"time": 1790,						"level": 9					},					{						"ability": 5401,						"time": 1830,						"level": 10					},					{						"ability": 5403,						"time": 1931,						"level": 11					},					{						"ability": 5401,						"time": 2176,						"level": 12					},					{						"ability": 5401,						"time": 2232,						"level": 13					},					{						"ability": 5401,						"time": 2509,						"level": 14					},					{						"ability": 5002,						"time": 2585,						"level": 15					},					{						"ability": 5403,						"time": 2725,						"level": 16					}				]							}		]		,		"radiant_win": false,		"duration": 2612,		"start_time": 1447518904,		"match_id": 1935495139,		"match_seq_num": 1710001738,		"tower_status_radiant": 6,		"tower_status_dire": 1572,		"barracks_status_radiant": 3,		"barracks_status_dire": 63,		"cluster": 224,		"first_blood_time": 0,		"lobby_type": 0,		"human_players": 10,		"leagueid": 0,		"positive_votes": 0,		"negative_votes": 0,		"game_mode": 4,		"engine": 1	}}